odoo9_addon_connector_job_subscribe-9.0.1.0.0-py2.7-nspkg.pth
odoo9_addon_connector_job_subscribe-9.0.1.0.0.dist-info/top_level.txt
odoo9_addon_connector_job_subscribe-9.0.1.0.0.dist-info/WHEEL
odoo9_addon_connector_job_subscribe-9.0.1.0.0.dist-info/RECORD
odoo9_addon_connector_job_subscribe-9.0.1.0.0.dist-info/metadata.json
odoo9_addon_connector_job_subscribe-9.0.1.0.0.dist-info/DESCRIPTION.rst
odoo9_addon_connector_job_subscribe-9.0.1.0.0.dist-info/METADATA
odoo9_addon_connector_job_subscribe-9.0.1.0.0.dist-info/namespace_packages.txt
odoo_addons/connector_job_subscribe/__openerp__.py
odoo_addons/connector_job_subscribe/__init__.py
odoo_addons/connector_job_subscribe/README.rst
odoo_addons/connector_job_subscribe/models/__init__.py
odoo_addons/connector_job_subscribe/models/res_users.py
odoo_addons/connector_job_subscribe/views/res_users_view.xml
odoo_addons/connector_job_subscribe/queue/__init__.py
odoo_addons/connector_job_subscribe/queue/model.py
odoo_addons/connector_job_subscribe/tests/__init__.py
odoo_addons/connector_job_subscribe/tests/test_job_subscribe.py
